darabonba/__init__.py
darabonba/core.py
darabonba/date.py
darabonba/decorators.py
darabonba/event.py
darabonba/exceptions.py
darabonba/file.py
darabonba/model.py
darabonba/number.py
darabonba/request.py
darabonba/response.py
darabonba/runtime.py
darabonba/url.py
darabonba/policy/__init__.py
darabonba/policy/retry.py
darabonba/utils/__init__.py
darabonba/utils/bytes.py
darabonba/utils/form.py
darabonba/utils/logger.py
darabonba/utils/map.py
darabonba/utils/stream.py
darabonba/utils/validation.py
darabonba/utils/xml.py
darabonba_core-1.0.3.dist-info/METADATA
darabonba_core-1.0.3.dist-info/WHEEL
darabonba_core-1.0.3.dist-info/top_level.txt
darabonba_core-1.0.3.dist-info/RECORD
